src/__init__.py
src/cli.py
src/context.py
src/response.py
src/server.py
src/tab.py
src/tools/__init__.py
src/tools/base.py
src/tools/common.py
src/tools/element.py
src/tools/navigate.py
src/tools/wait.py
drissionpage_mcp-0.1.0.dist-info/METADATA
drissionpage_mcp-0.1.0.dist-info/WHEEL
drissionpage_mcp-0.1.0.dist-info/entry_points.txt
drissionpage_mcp-0.1.0.dist-info/top_level.txt
drissionpage_mcp-0.1.0.dist-info/RECORD
