Metadata-Version: 2.4
Name: drissionpage-mcp
Version: 0.1.0
Summary: Professional browser automation for Claude Code and MCP clients powered by DrissionPage
Author-email: Wukunyun <864353360@qq.com>
License: Apache-2.0
Project-URL: Homepage, https://github.com/jumodada/DrissionMCP
Project-URL: Documentation, https://github.com/jumodada/DrissionMCP#readme
Project-URL: Repository, https://github.com/jumodada/DrissionMCP
Project-URL: Issues, https://github.com/jumodada/DrissionMCP/issues
Project-URL: Changelog, https://github.com/jumodada/DrissionMCP/blob/main/CHANGELOG.md
Keywords: mcp,model-context-protocol,claude,drissionpage,browser-automation,web-scraping,llm-tools,ai-automation
Classifier: Development Status :: 4 - Beta
Classifier: Intended Audience :: Developers
Classifier: License :: OSI Approved :: Apache Software License
Classifier: Operating System :: OS Independent
Classifier: Programming Language :: Python :: 3
Classifier: Programming Language :: Python :: 3.8
Classifier: Programming Language :: Python :: 3.9
Classifier: Programming Language :: Python :: 3.10
Classifier: Programming Language :: Python :: 3.11
Classifier: Programming Language :: Python :: 3.12
Classifier: Topic :: Software Development :: Libraries :: Python Modules
Classifier: Topic :: Internet :: WWW/HTTP :: Browsers
Classifier: Topic :: Scientific/Engineering :: Artificial Intelligence
Requires-Python: >=3.8
Requires-Dist: mcp>=1.0.0
Requires-Dist: DrissionPage>=4.0.0
Requires-Dist: pydantic>=2.0.0
Requires-Dist: typing-extensions>=4.0.0
Provides-Extra: dev
Requires-Dist: pytest>=7.0.0; extra == "dev"
Requires-Dist: pytest-asyncio>=0.21.0; extra == "dev"
Requires-Dist: pytest-cov>=4.0.0; extra == "dev"
Requires-Dist: black>=23.0.0; extra == "dev"
Requires-Dist: isort>=5.0.0; extra == "dev"
Requires-Dist: flake8>=6.0.0; extra == "dev"
Requires-Dist: mypy>=1.0.0; extra == "dev"
